JsonPydexer.py
JsonPydexer-0.3.0.dist-info/DESCRIPTION.rst
JsonPydexer-0.3.0.dist-info/METADATA
JsonPydexer-0.3.0.dist-info/RECORD
JsonPydexer-0.3.0.dist-info/WHEEL
JsonPydexer-0.3.0.dist-info/metadata.json
JsonPydexer-0.3.0.dist-info/top_level.txt
