Metadata-Version: 2.0
Name: JsonPydexer
Version: 0.3.0
Summary: A (python) indexer for large collections of json files
Home-page: http://github.com/cl3wis/JsonPydexer
Author: Christian Bailey (me@christianbailey.me)
Author-email: me@christianbailey.me
License: MPL 2.0
Keywords: json index
Platform: UNKNOWN
Classifier: Development Status :: 3 - Alpha
Classifier: Intended Audience :: Developers
Classifier: License :: OSI Approved :: Mozilla Public License 2.0 (MPL 2.0)
